LICENSE
MANIFEST.in
README.md
requirements.txt
setup.py
qseckey/__init__.py
qseckey/core.py
qseckey/routes.py
qseckey.egg-info/PKG-INFO
qseckey.egg-info/SOURCES.txt
qseckey.egg-info/dependency_links.txt
qseckey.egg-info/requires.txt
qseckey.egg-info/top_level.txt
qseckey/channels/__init__.py
qseckey/channels/public_channel.py
qseckey/channels/quantum_channel.py
qseckey/controllers/__init__.py
qseckey/controllers/key_manager.py
qseckey/controllers/qkd/__init__.py
qseckey/controllers/qkd/quantum_manager.py
qseckey/controllers/qkd/bb84/__init__.py
qseckey/controllers/qkd/bb84/bb84Utils.py
qseckey/controllers/qkd/bb84/bb84_key_generator.py
qseckey/controllers/qkd/bb84/communication_handler.py
qseckey/controllers/qkd/bb84/receiver.py
qseckey/controllers/qkd/bb84/sender.py
qseckey/services/__init__.py
qseckey/services/connection_storage_helper.py
qseckey/services/key_storage_helper.py
qseckey/services/quantum_simulator.py
qseckey/services/request_sender.py
qseckey/services/storage/__init__.py
qseckey/services/storage/connection_storage.py
qseckey/services/storage/key_storage.py
qseckey/utils/__init__.py
qseckey/utils/config.py
qseckey/utils/payload_generate.py