Metadata-Version: 2.4
Name: qseckey
Version: 0.1.2
Summary: QSECKEY: Quantum Secure Key generation library for classical KMS integration
Home-page: https://github.com/azadprajapat/qseckey.git
Author: Azad Prajapat
Author-email: azadprajapat4@gmail.com
Classifier: Programming Language :: Python :: 3
Classifier: License :: OSI Approved :: MIT License
Classifier: Operating System :: OS Independent
Requires-Python: >=3.7
License-File: LICENSE
Requires-Dist: fastapi
Requires-Dist: uvicorn
Requires-Dist: pydantic
Requires-Dist: python-dotenv
Requires-Dist: qiskit
Requires-Dist: qiskit-aer
Requires-Dist: numpy
Requires-Dist: qiskit_ibm_runtime
Dynamic: author
Dynamic: author-email
Dynamic: classifier
Dynamic: description
Dynamic: description-content-type
Dynamic: home-page
Dynamic: license-file
Dynamic: requires-dist
Dynamic: requires-python
Dynamic: summary
